manual_data_selector/__init__.py
manual_data_selector/cli.py
manual_data_selector/dash_lasso_data_selector.py
manual_data_selector/lasso_data_selector.py
manual_data_selector-0.1.2.dist-info/AUTHORS.rst
manual_data_selector-0.1.2.dist-info/LICENSE
manual_data_selector-0.1.2.dist-info/METADATA
manual_data_selector-0.1.2.dist-info/WHEEL
manual_data_selector-0.1.2.dist-info/entry_points.txt
manual_data_selector-0.1.2.dist-info/top_level.txt
manual_data_selector-0.1.2.dist-info/RECORD
