Metadata-Version: 2.1
Name: manual-data-selector
Version: 0.1.2
Summary: Python package to select data from scatter plots. The goal is to use specific selected data to train Machine Learning models.
Home-page: https://github.com/WEILMAX/manual_data_selector
Author: Maximillian Weil
Author-email: maximillian.weil@vub.be
License: MIT license
Keywords: manual_data_selector
Classifier: Development Status :: 2 - Pre-Alpha
Classifier: Intended Audience :: Developers
Classifier: License :: OSI Approved :: MIT License
Classifier: Natural Language :: English
Classifier: Programming Language :: Python :: 3
Classifier: Programming Language :: Python :: 3.6
Classifier: Programming Language :: Python :: 3.7
Classifier: Programming Language :: Python :: 3.8
Requires-Python: >=3.6
License-File: LICENSE
License-File: AUTHORS.rst
Requires-Dist: Click >=7.0
Requires-Dist: ipywidgets
Requires-Dist: plotly
Requires-Dist: pandas
Requires-Dist: numpy
Requires-Dist: matplotlib
Requires-Dist: dash
